auth/__init__.py
auth/data.py
auth/guards.py
auth/loaders.py
auth/middleware.py
auth/plugin.py
auth/api/__init__.py
auth/api/account_controller.py
auth/api/e2e_controller.py
auth/api/permission_controller.py
auth/api/role_controller.py
auth/api/user_controller.py
auth/models/__init__.py
auth/models/auth_code_model.py
auth/models/permission_model.py
auth/models/role_model.py
auth/models/role_permission_model.py
auth/models/user_model.py
auth/models/user_role_model.py
auth/services/__init__.py
auth/services/auth_service.py
auth/services/permission_service.py
auth/services/role_service.py
auth/services/user_service.py
core/cli.py
core/database.py
core/mail.py
core/openapi.py
core/settings.py
core/storage.py
service_packages-5.0.1.dist-info/METADATA
service_packages-5.0.1.dist-info/WHEEL
service_packages-5.0.1.dist-info/licenses/LICENSE.txt
service_packages-5.0.1.dist-info/RECORD
