Metadata-Version: 2.4
Name: service_packages
Version: 5.0.1
Summary: Service laboratory packages
Author-email: Alexei Rysev <alexeirysev@gmail.com>
Maintainer-email: Alexei Rysev <alexeirysev@gmail.com>
License: Copyright (c) 2018 The Python Packaging Authority
License-File: LICENSE.txt
Keywords: development,prototype,setuptools
Classifier: Development Status :: 3 - Alpha
Classifier: Intended Audience :: Developers
Classifier: License :: OSI Approved :: MIT License
Classifier: Programming Language :: Python :: 3
Classifier: Programming Language :: Python :: 3 :: Only
Classifier: Programming Language :: Python :: 3.12
Classifier: Programming Language :: Python :: 3.13
Classifier: Topic :: Software Development :: Build Tools
Requires-Python: >=3.12
Requires-Dist: advanced-alchemy==1.4.4
Requires-Dist: asyncpg>=0.30.0
Requires-Dist: bcrypt>=5.0.0
Requires-Dist: faststream[nats]>=0.6.3
Requires-Dist: litestar[standard]>=2.15.2
Requires-Dist: loguru>=0.7.3
Requires-Dist: pydantic-settings>=2.8.1
Requires-Dist: pydantic>=2.11.3
Requires-Dist: pyjwt>=2.10.1
Requires-Dist: pytest-asyncio>=0.24.0
Requires-Dist: pytest-cov>=7.0.0
Requires-Dist: pytest-env>=1.2.0
Requires-Dist: pytest-html>=4.1.1
Requires-Dist: pytest>=8.4.2
Requires-Dist: pyyaml>=6.0.3
Requires-Dist: sqlalchemy>=2.0.40
Requires-Dist: timer-context>=1.1.1
Requires-Dist: uvicorn>=0.34.1
Provides-Extra: dev
Requires-Dist: check-manifest; extra == 'dev'
Provides-Extra: test
Requires-Dist: coverage; extra == 'test'
Requires-Dist: pytest-asyncio==0.24.0; extra == 'test'
Requires-Dist: pytest>=8.2.1; extra == 'test'
